{
  "project_info": {
    "project_number": "3474585180",
    "project_id": "topswimmerdb",
    "storage_bucket": "topswimmerdb.appspot.com"
  },
  "client": [
    {
      "client_info": {
        "mobilesdk_app_id": "1:3474585180:android:a41d5705127d88ee265899",
        "android_client_info": {
          "package_name": "com.example.topswimmer"
        }
      },
      "oauth_client": [
        {
          "client_id": "3474585180-e0l4ajsagitnt64m7fm1d8aah6i5m418.apps.googleusercontent.com",
          "client_type": 1,
          "android_info": {
            "package_name": "com.example.topswimmer",
            "certificate_hash": "1c63727dd2abedc541fc24d63941e9f92df14df2"
          }
        },
        {
          "client_id": "3474585180-nobm3ounjiimljnm9et52j8urhh1ge04.apps.googleusercontent.com",
          "client_type": 3
        }
      ],
      "api_key": [
        {
          "current_key": "AIzaSyBNXWquKVyPfkSp04CQuyaXO2N0rNpkB7I"
        }
      ],
      "services": {
        "appinvite_service": {
          "other_platform_oauth_client": [
            {
              "client_id": "3474585180-nobm3ounjiimljnm9et52j8urhh1ge04.apps.googleusercontent.com",
              "client_type": 3
            },
            {
              "client_id": "3474585180-8s257ijjmlpfk8mt894fbljim5b0d92r.apps.googleusercontent.com",
              "client_type": 2,
              "ios_info": {
                "bundle_id": "com.example.topswimmerNew"
              }
            }
          ]
        }
      }
    }
  ],
  "configuration_version": "1"
}